primus_lens_workload_exporter/__init__.py
primus_lens_workload_exporter/main.py
primus_lens_workload_exporter/collector/__init__.py
primus_lens_workload_exporter/collector/collector.py
primus_lens_workload_exporter/gpu/__init__.py
primus_lens_workload_exporter/gpu/gpu_metrics.py
primus_lens_workload_exporter/metric/__init__.py
primus_lens_workload_exporter/metric/collector.py
primus_lens_workload_exporter/rdma/__init__.py
primus_lens_workload_exporter/rdma/rdma.py
primus_lens_workload_exporter-0.1.0.dist-info/METADATA
primus_lens_workload_exporter-0.1.0.dist-info/WHEEL
primus_lens_workload_exporter-0.1.0.dist-info/top_level.txt
primus_lens_workload_exporter-0.1.0.dist-info/RECORD
