Metadata-Version: 2.4
Name: primus_lens_workload_exporter
Version: 0.1.0
Summary: Add your description here
Requires-Python: >=3.10
Requires-Dist: wheel>=0.45.1
